flux_config_shared/__init__.py
flux_config_shared/app_config.py
flux_config_shared/config_locations.py
flux_config_shared/daemon_state.py
flux_config_shared/delegate_config.py
flux_config_shared/log.py
flux_config_shared/models.py
flux_config_shared/protocol.py
flux_config_shared/user_config.py
flux_config_shared-0.1.1.dist-info/WHEEL
flux_config_shared-0.1.1.dist-info/METADATA
flux_config_shared-0.1.1.dist-info/RECORD
