Metadata-Version: 2.3
Name: flux-config-shared
Version: 0.1.1
Summary: Shared protocol and configuration definitions for Flux Config packages
Author: David White
Author-email: David White <david@runonflux.io>
License: GPL-3.0-or-later
Classifier: Development Status :: 4 - Beta
Classifier: Intended Audience :: System Administrators
Classifier: License :: OSI Approved :: GNU General Public License v3 or later (GPLv3+)
Classifier: Programming Language :: Python :: 3
Classifier: Programming Language :: Python :: 3.13
Classifier: Topic :: System :: Systems Administration
Classifier: Topic :: System :: Monitoring
Requires-Dist: pyyaml>=6.0.2,<7
Requires-Dist: aiofiles>=25.1.0,<26
Requires-Dist: textual>=6.11.0,<7
Requires-Dist: pydantic>=2.10.6,<3
Requires-Dist: sshpubkeys>=3.3.1,<4
Requires-Dist: email-validator>=2.2.0,<2.3
Requires-Dist: pyrage>=1.3.0
Requires-Dist: flux-delegate-starter>=0.1.0
Requires-Python: >=3.13, <4
